boto3_missing.pth
boto3_missing/__init__.py
boto3_missing/data/dynamodb/2012-08-10/resources-1.sdk-extras.json
boto3_missing-0.1.0.dist-info/LICENSE.txt
boto3_missing-0.1.0.dist-info/METADATA
boto3_missing-0.1.0.dist-info/WHEEL
boto3_missing-0.1.0.dist-info/top_level.txt
boto3_missing-0.1.0.dist-info/RECORD
