Metadata-Version: 2.1
Name: boto3-missing
Version: 0.1.0
Summary: Add missing DynamoDB service resource methods to boto3
Author-email: Leo Singer <leo.p.singer@nasa.gov>
License: Apache-2.0
Project-URL: source, https://github.com/nasa-gcn/boto3-missing
Classifier: Intended Audience :: Developers
Classifier: Intended Audience :: Information Technology
Classifier: Topic :: Database
Requires-Python: >=3.9
License-File: LICENSE.txt
